ynab_tui/__init__.py
ynab_tui/config.py
ynab_tui/main.py
ynab_tui/py.typed
ynab_tui/cli/__init__.py
ynab_tui/cli/formatters.py
ynab_tui/cli/helpers.py
ynab_tui/clients/__init__.py
ynab_tui/clients/amazon_client.py
ynab_tui/clients/decorators.py
ynab_tui/clients/mock_ynab_client.py
ynab_tui/clients/protocols.py
ynab_tui/clients/ynab_client.py
ynab_tui/db/__init__.py
ynab_tui/db/database.py
ynab_tui/db/models.py
ynab_tui/db/protocols.py
ynab_tui/db/mixins/__init__.py
ynab_tui/db/mixins/amazon.py
ynab_tui/db/mixins/base.py
ynab_tui/db/mixins/categories.py
ynab_tui/db/mixins/history.py
ynab_tui/db/mixins/pending.py
ynab_tui/db/mixins/sync.py
ynab_tui/db/mixins/transactions.py
ynab_tui/mock_data/categories.csv
ynab_tui/mock_data/generate_mock_data.py
ynab_tui/mock_data/orders.csv
ynab_tui/mock_data/transactions.csv
ynab_tui/models/__init__.py
ynab_tui/models/category.py
ynab_tui/models/order.py
ynab_tui/models/transaction.py
ynab_tui/services/__init__.py
ynab_tui/services/amazon_matcher.py
ynab_tui/services/categorizer.py
ynab_tui/services/category_mapping.py
ynab_tui/services/history.py
ynab_tui/services/matcher.py
ynab_tui/services/protocols.py
ynab_tui/services/sync.py
ynab_tui/services/matching/__init__.py
ynab_tui/services/matching/algorithms.py
ynab_tui/services/matching/types.py
ynab_tui/tui/__init__.py
ynab_tui/tui/app.py
ynab_tui/tui/constants.py
ynab_tui/tui/dependencies.py
ynab_tui/tui/handlers.py
ynab_tui/tui/state.py
ynab_tui/tui/mixins/__init__.py
ynab_tui/tui/mixins/navigation.py
ynab_tui/tui/modals/__init__.py
ynab_tui/tui/modals/budget_picker.py
ynab_tui/tui/modals/category_filter.py
ynab_tui/tui/modals/category_picker.py
ynab_tui/tui/modals/fuzzy_select.py
ynab_tui/tui/modals/memo_edit.py
ynab_tui/tui/modals/payee_filter.py
ynab_tui/tui/modals/transaction_search.py
ynab_tui/tui/screens/__init__.py
ynab_tui/tui/screens/item_split.py
ynab_tui/tui/screens/push_preview.py
ynab_tui/tui/screens/settings.py
ynab_tui/tui/widgets/__init__.py
ynab_tui-0.1.1.dist-info/METADATA
ynab_tui-0.1.1.dist-info/WHEEL
ynab_tui-0.1.1.dist-info/entry_points.txt
ynab_tui-0.1.1.dist-info/licenses/LICENSE
ynab_tui-0.1.1.dist-info/RECORD
