Metadata-Version: 2.4
Name: ynab-tui
Version: 0.1.1
Summary: YNAB transaction categorizer with Amazon order matching
Project-URL: Repository, https://github.com/esterhui/ynab-tui
Project-URL: Issues, https://github.com/esterhui/ynab-tui/issues
Project-URL: Changelog, https://github.com/esterhui/ynab-tui/blob/main/CHANGELOG.md
Author: Stephan Esterhuizen
License: MIT
License-File: LICENSE
Keywords: amazon,budget,categorization,terminal,tui,ynab
Classifier: Development Status :: 4 - Beta
Classifier: Environment :: Console
Classifier: License :: OSI Approved :: MIT License
Classifier: Operating System :: OS Independent
Classifier: Programming Language :: Python :: 3
Classifier: Programming Language :: Python :: 3.11
Classifier: Topic :: Office/Business :: Financial
Classifier: Typing :: Typed
Requires-Python: <3.12,>=3.11
Requires-Dist: amazon-orders>=1.0.0
Requires-Dist: click>=8.0.0
Requires-Dist: rich>=13.0.0
Requires-Dist: textual>=1.0.0
Requires-Dist: tomli>=2.0.0
Requires-Dist: tqdm>=4.66.0
Requires-Dist: ynab>=1.9.0
Provides-Extra: dev
Requires-Dist: mypy>=1.13.0; extra == 'dev'
Requires-Dist: pytest-asyncio>=0.23.0; extra == 'dev'
Requires-Dist: pytest-cov>=6.0.0; extra == 'dev'
Requires-Dist: pytest-xdist>=3.5.0; extra == 'dev'
Requires-Dist: pytest>=8.0.0; extra == 'dev'
Requires-Dist: ruff>=0.8.0; extra == 'dev'
